erfa/version.py
erfa/_version.py
erfa/__init__.py
erfa/core.py
erfa/ufunc.abi3.so
erfa/helpers.py
erfa/tests/__init__.py
erfa/tests/test_ufunc.py
erfa/tests/test_erfa.py
pyerfa-2.0.1.3.dist-info/RECORD
pyerfa-2.0.1.3.dist-info/WHEEL
pyerfa-2.0.1.3.dist-info/LICENSE.rst
pyerfa-2.0.1.3.dist-info/top_level.txt
pyerfa-2.0.1.3.dist-info/METADATA
