Metadata-Version: 2.1
Name: pyerfa
Version: 2.0.1.3
Summary: Python bindings for ERFA
Home-page: https://github.com/liberfa/pyerfa
Author: The PyERFA Developers
License: BSD 3-Clause License
Keywords: astronomy,astrophysics,cosmology,space,science,coordinate
Classifier: Intended Audience :: Science/Research
Classifier: License :: OSI Approved :: BSD License
Classifier: Operating System :: OS Independent
Classifier: Programming Language :: C
Classifier: Programming Language :: Python :: 3
Classifier: Programming Language :: Python :: Implementation :: CPython
Classifier: Topic :: Scientific/Engineering :: Astronomy
Classifier: Topic :: Scientific/Engineering :: Physics
Requires-Python: >=3.9
License-File: LICENSE.rst
Requires-Dist: numpy>=1.19
Provides-Extra: test
Requires-Dist: pytest; extra == "test"
Requires-Dist: pytest-doctestplus>=0.7; extra == "test"
Provides-Extra: docs
Requires-Dist: sphinx-astropy>=1.3; extra == "docs"
